oswhich/__init__.py
oswhich/oswhich.py
oswhich-0.1.0.dist-info/LICENSE
oswhich-0.1.0.dist-info/METADATA
oswhich-0.1.0.dist-info/WHEEL
oswhich-0.1.0.dist-info/top_level.txt
oswhich-0.1.0.dist-info/RECORD
