Metadata-Version: 2.1
Name: oswhich
Version: 0.1.0
Summary: {description}
Home-page: UNKNOWN
Author: Pedro Maciel Xavier
Author-email: pedromxavier@poli.ufrj.br
License: UNKNOWN
Platform: UNKNOWN
Classifier: Programming Language :: Python :: 3
Requires-Python: <4,>=3.7
